contabilib/__init__.py
contabilib/calcular_balanco.py
contabilib/calcular_rescisao.py
contabilib/exportar_pdf.py
contabilib/grafico.py
contabilib-5.3.0.dist-info/METADATA
contabilib-5.3.0.dist-info/WHEEL
contabilib-5.3.0.dist-info/top_level.txt
contabilib-5.3.0.dist-info/RECORD
