Metadata-Version: 2.1
Name: contabilib
Version: 5.3.0
Summary: Biblioteca para cálculos contábeis.
Author: crisly, erik
Author-email: crislymaria21@gmail.com
Keywords: python,contablidade
Classifier: Development Status :: 3 - Alpha
Requires-Dist: numpy
Requires-Dist: matplotlib
Requires-Dist: seaborn
Requires-Dist: fpdf
